setup.py
playlist/__init__.py
playlist/m3u.py
playlist.egg-info/PKG-INFO
playlist.egg-info/SOURCES.txt
playlist.egg-info/dependency_links.txt
playlist.egg-info/top_level.txt