Metadata-Version: 1.0
Name: playlist
Version: 0.1.0
Summary: Media playlist API and utilities
Home-page: http://bitbucket.org/esmljaos/playlist/wiki/Home
Author: Jacob Oscarson
Author-email: jacob@aspektratio.net
License: GNU LGPL
Platform: UNKNOWN
